django_tooling/__init__.py
django_tooling/db.py
django_tooling/exceptions.py
django_tooling/moduleloading.py
django_tooling/preconditions.py
django_tooling/registeradmin.py
django_tooling/management/__init__.py
django_tooling/management/commands/__init__.py
django_tooling/management/commands/resetdb.py
django_tooling-0.9.6.dist-info/LICENSE.md
django_tooling-0.9.6.dist-info/METADATA
django_tooling-0.9.6.dist-info/WHEEL
django_tooling-0.9.6.dist-info/top_level.txt
django_tooling-0.9.6.dist-info/RECORD
